{
  "version": 1,
  "functions": {
    "/_middleware": {
      "runtime": "nodejs",
      "matchers": [
        {
          "regexp": "^(?:\\/(_next\\/data\\/[^/]{1,}))?\\/dashboard(?:\\/((?:[^\\/#\\?]+?)(?:\\/(?:[^\\/#\\?]+?))*))?(\\.json|\\.rsc|\\.segments\\/.+\\.segment\\.rsc)?[\\/#\\?]?$",
          "originalSource": "/dashboard/:path*"
        },
        {
          "regexp": "^(?:\\/(_next\\/data\\/[^/]{1,}))?\\/chat(?:\\/((?:[^\\/#\\?]+?)(?:\\/(?:[^\\/#\\?]+?))*))?(\\.json|\\.rsc|\\.segments\\/.+\\.segment\\.rsc)?[\\/#\\?]?$",
          "originalSource": "/chat/:path*"
        },
        {
          "regexp": "^(?:\\/(_next\\/data\\/[^/]{1,}))?\\/upload(?:\\/((?:[^\\/#\\?]+?)(?:\\/(?:[^\\/#\\?]+?))*))?(\\.json|\\.rsc|\\.segments\\/.+\\.segment\\.rsc)?[\\/#\\?]?$",
          "originalSource": "/upload/:path*"
        },
        {
          "regexp": "^(?:\\/(_next\\/data\\/[^/]{1,}))?\\/schedule(?:\\/((?:[^\\/#\\?]+?)(?:\\/(?:[^\\/#\\?]+?))*))?(\\.json|\\.rsc|\\.segments\\/.+\\.segment\\.rsc)?[\\/#\\?]?$",
          "originalSource": "/schedule/:path*"
        },
        {
          "regexp": "^(?:\\/(_next\\/data\\/[^/]{1,}))?\\/progress(?:\\/((?:[^\\/#\\?]+?)(?:\\/(?:[^\\/#\\?]+?))*))?(\\.json|\\.rsc|\\.segments\\/.+\\.segment\\.rsc)?[\\/#\\?]?$",
          "originalSource": "/progress/:path*"
        },
        {
          "regexp": "^(?:\\/(_next\\/data\\/[^/]{1,}))?\\/login(\\.json|\\.rsc|\\.segments\\/.+\\.segment\\.rsc)?[\\/#\\?]?$",
          "originalSource": "/login"
        },
        {
          "regexp": "^(?:\\/(_next\\/data\\/[^/]{1,}))?\\/signup(\\.json|\\.rsc|\\.segments\\/.+\\.segment\\.rsc)?[\\/#\\?]?$",
          "originalSource": "/signup"
        }
      ]
    }
  }
}