[
  {
    "route": "/chat",
    "firstLoadUncompressedJsBytes": 1258705,
    "firstLoadChunkPaths": [
      ".next\\static\\chunks\\0jdj7fljdvzcj.js",
      ".next\\static\\chunks\\03ms1ezt0dgn8.js",
      ".next\\static\\chunks\\0yy5uag88ia8p.js",
      ".next\\static\\chunks\\10l9be3_xvm03.js",
      ".next\\static\\chunks\\00b0btqikyhdc.js",
      ".next\\static\\chunks\\0ns4zb27ct6qm.js",
      ".next\\static\\chunks\\0eb5qdkdxm7yu.js",
      ".next\\static\\chunks\\0jjlxapz19zo6.js",
      ".next\\static\\chunks\\08fty6cel22-l.js",
      ".next\\static\\chunks\\turbopack-0wc4csre.b8cy.js"
    ]
  },
  {
    "route": "/dashboard",
    "firstLoadUncompressedJsBytes": 807349,
    "firstLoadChunkPaths": [
      ".next\\static\\chunks\\0jdj7fljdvzcj.js",
      ".next\\static\\chunks\\03ms1ezt0dgn8.js",
      ".next\\static\\chunks\\0yy5uag88ia8p.js",
      ".next\\static\\chunks\\10l9be3_xvm03.js",
      ".next\\static\\chunks\\0hgjccz9ytykq.js",
      ".next\\static\\chunks\\0eb5qdkdxm7yu.js",
      ".next\\static\\chunks\\0jjlxapz19zo6.js",
      ".next\\static\\chunks\\08fty6cel22-l.js",
      ".next\\static\\chunks\\turbopack-0wc4csre.b8cy.js"
    ]
  },
  {
    "route": "/progress",
    "firstLoadUncompressedJsBytes": 807349,
    "firstLoadChunkPaths": [
      ".next\\static\\chunks\\0jdj7fljdvzcj.js",
      ".next\\static\\chunks\\03ms1ezt0dgn8.js",
      ".next\\static\\chunks\\0yy5uag88ia8p.js",
      ".next\\static\\chunks\\10l9be3_xvm03.js",
      ".next\\static\\chunks\\0ns4zb27ct6qm.js",
      ".next\\static\\chunks\\0eb5qdkdxm7yu.js",
      ".next\\static\\chunks\\0jjlxapz19zo6.js",
      ".next\\static\\chunks\\08fty6cel22-l.js",
      ".next\\static\\chunks\\turbopack-0wc4csre.b8cy.js"
    ]
  },
  {
    "route": "/schedule",
    "firstLoadUncompressedJsBytes": 807349,
    "firstLoadChunkPaths": [
      ".next\\static\\chunks\\0jdj7fljdvzcj.js",
      ".next\\static\\chunks\\03ms1ezt0dgn8.js",
      ".next\\static\\chunks\\0yy5uag88ia8p.js",
      ".next\\static\\chunks\\10l9be3_xvm03.js",
      ".next\\static\\chunks\\0ns4zb27ct6qm.js",
      ".next\\static\\chunks\\0eb5qdkdxm7yu.js",
      ".next\\static\\chunks\\0jjlxapz19zo6.js",
      ".next\\static\\chunks\\08fty6cel22-l.js",
      ".next\\static\\chunks\\turbopack-0wc4csre.b8cy.js"
    ]
  },
  {
    "route": "/upload",
    "firstLoadUncompressedJsBytes": 807349,
    "firstLoadChunkPaths": [
      ".next\\static\\chunks\\0jdj7fljdvzcj.js",
      ".next\\static\\chunks\\03ms1ezt0dgn8.js",
      ".next\\static\\chunks\\0yy5uag88ia8p.js",
      ".next\\static\\chunks\\10l9be3_xvm03.js",
      ".next\\static\\chunks\\0ns4zb27ct6qm.js",
      ".next\\static\\chunks\\0eb5qdkdxm7yu.js",
      ".next\\static\\chunks\\0jjlxapz19zo6.js",
      ".next\\static\\chunks\\08fty6cel22-l.js",
      ".next\\static\\chunks\\turbopack-0wc4csre.b8cy.js"
    ]
  },
  {
    "route": "/signup",
    "firstLoadUncompressedJsBytes": 799879,
    "firstLoadChunkPaths": [
      ".next\\static\\chunks\\0jdj7fljdvzcj.js",
      ".next\\static\\chunks\\03ms1ezt0dgn8.js",
      ".next\\static\\chunks\\0yy5uag88ia8p.js",
      ".next\\static\\chunks\\0ayln7y0.8.q..js",
      ".next\\static\\chunks\\17m-zqz955p9k.js",
      ".next\\static\\chunks\\0eb5qdkdxm7yu.js",
      ".next\\static\\chunks\\0jjlxapz19zo6.js",
      ".next\\static\\chunks\\08fty6cel22-l.js",
      ".next\\static\\chunks\\turbopack-0wc4csre.b8cy.js"
    ]
  },
  {
    "route": "/login",
    "firstLoadUncompressedJsBytes": 799221,
    "firstLoadChunkPaths": [
      ".next\\static\\chunks\\0jdj7fljdvzcj.js",
      ".next\\static\\chunks\\03ms1ezt0dgn8.js",
      ".next\\static\\chunks\\0yy5uag88ia8p.js",
      ".next\\static\\chunks\\06cjsy3zz9rb1.js",
      ".next\\static\\chunks\\17m-zqz955p9k.js",
      ".next\\static\\chunks\\0eb5qdkdxm7yu.js",
      ".next\\static\\chunks\\0jjlxapz19zo6.js",
      ".next\\static\\chunks\\08fty6cel22-l.js",
      ".next\\static\\chunks\\turbopack-0wc4csre.b8cy.js"
    ]
  },
  {
    "route": "/",
    "firstLoadUncompressedJsBytes": 759063,
    "firstLoadChunkPaths": [
      ".next\\static\\chunks\\0jdj7fljdvzcj.js",
      ".next\\static\\chunks\\03ms1ezt0dgn8.js",
      ".next\\static\\chunks\\0yy5uag88ia8p.js",
      ".next\\static\\chunks\\0eb5qdkdxm7yu.js",
      ".next\\static\\chunks\\0jjlxapz19zo6.js",
      ".next\\static\\chunks\\08fty6cel22-l.js",
      ".next\\static\\chunks\\turbopack-0wc4csre.b8cy.js"
    ]
  },
  {
    "route": "/_not-found",
    "firstLoadUncompressedJsBytes": 759063,
    "firstLoadChunkPaths": [
      ".next\\static\\chunks\\0jdj7fljdvzcj.js",
      ".next\\static\\chunks\\03ms1ezt0dgn8.js",
      ".next\\static\\chunks\\0yy5uag88ia8p.js",
      ".next\\static\\chunks\\0eb5qdkdxm7yu.js",
      ".next\\static\\chunks\\0jjlxapz19zo6.js",
      ".next\\static\\chunks\\08fty6cel22-l.js",
      ".next\\static\\chunks\\turbopack-0wc4csre.b8cy.js"
    ]
  }
]